AUTHORS
CHANGELOG
LICENSE
MANIFEST.in
README.rst
setup.py
bin/socrates
socrates/__init__.py
socrates/exceptions.py
socrates/models.py
socrates/processors.py
socrates/renderers.py
socrates/smartypants.py
socrates/socrates.py
socrates/typography.py
socrates/utils.py
socrates.egg-info/PKG-INFO
socrates.egg-info/SOURCES.txt
socrates.egg-info/dependency_links.txt
socrates.egg-info/requires.txt
socrates.egg-info/top_level.txt
socrates/themes/default/config.yaml
socrates/themes/default/layout/archive.html
socrates/themes/default/layout/atom.html
socrates/themes/default/layout/base.html
socrates/themes/default/layout/category.html
socrates/themes/default/layout/index.html
socrates/themes/default/layout/index_paged.html
socrates/themes/default/layout/page.html
socrates/themes/default/layout/single.html
socrates/themes/default/layout/sitemap.xml
socrates/themes/default/layout/media/style.css
socrates/themes/default/pages/about.md
socrates/themes/default/posts/2011-02-11-why-nokia-chose-windows-over-android.md
socrates/themes/jinja2/config.yaml
socrates/themes/jinja2/layout/archive.html
socrates/themes/jinja2/layout/atom.html
socrates/themes/jinja2/layout/base.html
socrates/themes/jinja2/layout/category.html
socrates/themes/jinja2/layout/index.html
socrates/themes/jinja2/layout/index_paged.html
socrates/themes/jinja2/layout/page.html
socrates/themes/jinja2/layout/single.html
socrates/themes/jinja2/layout/sitemap.xml
socrates/themes/jinja2/layout/media/style.css
socrates/themes/jinja2/pages/about.md
socrates/themes/jinja2/posts/2011-02-11-why-nokia-chose-windows-over-android.md