Metadata-Version: 1.0
Name: socrates
Version: 0.9.0
Summary: Socrates is a simple static site generator.
Home-page: http://honza.github.com/socrates/
Author: Honza Pokorny
Author-email: me@honza.ca
License: UNKNOWN
Platform: UNKNOWN
